{
    "prepare_queue": {
        "installed": [],
        "uninstalled": []
    },
    "config_munge": {
        "files": {}
    },
    "installed_plugins": {
        "cordova-plugin-barcodescanner": {
            "PACKAGE_NAME": "Flynn"
        },
        "cordova-plugin-console": {
            "PACKAGE_NAME": "Flynn"
        },
        "cordova-plugin-crosswalk-webview": {
            "PACKAGE_NAME": "Flynn"
        },
        "cordova-plugin-device": {
            "PACKAGE_NAME": "Flynn"
        },
        "cordova-plugin-dialogs": {
            "PACKAGE_NAME": "Flynn"
        },
        "cordova-plugin-email": {
            "PACKAGE_NAME": "Flynn"
        },
        "cordova-plugin-inappbrowser": {
            "PACKAGE_NAME": "Flynn"
        },
        "cordova-plugin-splashscreen": {
            "PACKAGE_NAME": "Flynn"
        },
        "cordova-plugin-urlhandler": {
            "URL_SCHEME": "flynnApp",
            "PACKAGE_NAME": "Flynn"
        },
        "cordova-plugin-whitelist": {
            "PACKAGE_NAME": "Flynn"
        },
        "cordova-plugin-android-support-v4": {
            "PACKAGE_NAME": "Flynn"
        },
        "ionic-plugin-keyboard": {
            "PACKAGE_NAME": "Flynn"
        },
        "cordova-sqlite-storage": {
            "PACKAGE_NAME": "Flynn"
        }
    },
    "dependent_plugins": {}
}